cacofonisk/__init__.py
cacofonisk/bridge.py
cacofonisk/callerid.py
cacofonisk/channel.py
cacofonisk/constants.py
cacofonisk/handlers.py
cacofonisk/reporters.py
cacofonisk/runners/__init__.py
cacofonisk/runners/ami_runner.py
cacofonisk/runners/file_runner.py
cacofonisk/utils/__init__.py
cacofonisk/utils/testcases.py
tests/__init__.py
tests/replaytest.py
tests/test_mobile.py
tests/test_originate.py
tests/test_partial.py
tests/test_queue.py
tests/test_reporters.py
tests/test_simple.py
tests/test_var_set.py
tests/test_xfer_attended.py
tests/test_xfer_blind.py
tests/test_xfer_blonde.py
tests/test_xfer_misc.py
tests/test_xfer_threeway.py
cacofonisk-0.7.10.dist-info/AUTHORS.md
cacofonisk-0.7.10.dist-info/LICENSE
cacofonisk-0.7.10.dist-info/METADATA
cacofonisk-0.7.10.dist-info/WHEEL
cacofonisk-0.7.10.dist-info/top_level.txt
cacofonisk-0.7.10.dist-info/RECORD
