Metadata-Version: 2.1
Name: cacofonisk
Version: 0.7.10
Summary: Track channels through Asterisk Management Interface (AMI)
Home-page: https://github.com/VoIPGRID/cacofonisk
Download-URL: https://github.com/VoIPGRID/cacofonisk/archive/0.7.10.tar.gz
Author: Devhouse Spindle
Author-email: opensource+cacofonisk@wearespindle.com
License: MIT
Keywords: ami asterisk callerid
Classifier: Development Status :: 4 - Beta
Classifier: Intended Audience :: Developers
Classifier: Topic :: Communications :: Telephony
Classifier: License :: OSI Approved :: MIT License
Classifier: Programming Language :: Python :: 3.4
Classifier: Programming Language :: Python :: 3.5
Classifier: Programming Language :: Python :: 3.6
License-File: LICENSE
License-File: AUTHORS.md
Requires-Dist: panoramisk <2,>=1.0
Provides-Extra: dev
Requires-Dist: check-manifest ; extra == 'dev'
Provides-Extra: test
Requires-Dist: coverage ; extra == 'test'
